{
  "@context": "http://iiif.io/api/presentation/3/context.json",
  "id": "https://lgsump.github.io/radio-venceremos-espanol/annotations/31-de-diciembre-1981-am-canvas-1-radio-venceremos.json",
  "type": "AnnotationPage",
  "label": "Radio Venceremos",
  "items": [
    {
      "@context": "http://www.w3.org/ns/anno.jsonld",
      "id": "31-de-diciembre-1981-am-canvas-1-radio-venceremos-annotation-0.json",
      "type": "Annotation",
      "motivation": [
        "supplementing",
        "commenting"
      ],
      "body": {
        "type": "TextualBody",
        "value": "Transmite Radio Venceremos, voz oficial del Frente Farabundo Martí para la Liberación Nacional. Emitiendo su señal de libertad desde El Salvador, Centroamérica, territorio en combate contra la opresión y el imperialismo.",
        "format": "text/plain",
        "purpose": "commenting"
      },
      "target": {
        "source": "https://lgsump.github.io/radio-venceremos-espanol/31-de-diciembre-1981-am/canvas-1/canvas",
        "selector": {
          "type": "RangeSelector",
          "t": "66.0,87.0"
        }
      }
    },
    {
      "@context": "http://www.w3.org/ns/anno.jsonld",
      "id": "31-de-diciembre-1981-am-canvas-1-radio-venceremos-annotation-1.json",
      "type": "Annotation",
      "motivation": [
        "supplementing",
        "commenting"
      ],
      "body": {
        "type": "TextualBody",
        "value": "Radio Venceremos, voz oficial del Frente Farabundo Martí para la Liberación Nacional, emite su señal de libertad desde el Frente Oriental Francisco Sánchez que comprende los departamentos salvadoreños de Usulután, San Miguel, La Unión y Morazán.",
        "format": "text/plain",
        "purpose": "commenting"
      },
      "target": {
        "source": "https://lgsump.github.io/radio-venceremos-espanol/31-de-diciembre-1981-am/canvas-1/canvas",
        "selector": {
          "type": "RangeSelector",
          "t": "109.0,131.0"
        }
      }
    },
    {
      "@context": "http://www.w3.org/ns/anno.jsonld",
      "id": "31-de-diciembre-1981-am-canvas-1-radio-venceremos-annotation-2.json",
      "type": "Annotation",
      "motivation": [
        "supplementing",
        "commenting"
      ],
      "body": {
        "type": "TextualBody",
        "value": "Radio Venceremos, expresión del poder popular sobre territorios controlados transmite desde Morazán todos los días de 6:00 AM a 7:00 AM y de 6:00 PM a 7:00 PM a través de la frecuencia internacional de los 40 metros 7 megahercios.",
        "format": "text/plain",
        "purpose": "commenting"
      },
      "target": {
        "source": "https://lgsump.github.io/radio-venceremos-espanol/31-de-diciembre-1981-am/canvas-1/canvas",
        "selector": {
          "type": "RangeSelector",
          "t": "147.0,171.0"
        }
      }
    },
    {
      "@context": "http://www.w3.org/ns/anno.jsonld",
      "id": "31-de-diciembre-1981-am-canvas-1-radio-venceremos-annotation-3.json",
      "type": "Annotation",
      "motivation": [
        "supplementing",
        "commenting"
      ],
      "body": {
        "type": "TextualBody",
        "value": "Nuestro apartado postal, 7-907, México, Distrito Federal.",
        "format": "text/plain",
        "purpose": "commenting"
      },
      "target": {
        "source": "https://lgsump.github.io/radio-venceremos-espanol/31-de-diciembre-1981-am/canvas-1/canvas",
        "selector": {
          "type": "RangeSelector",
          "t": "178.0,188.0"
        }
      }
    },
    {
      "@context": "http://www.w3.org/ns/anno.jsonld",
      "id": "31-de-diciembre-1981-am-canvas-1-radio-venceremos-annotation-4.json",
      "type": "Annotation",
      "motivation": [
        "supplementing",
        "commenting"
      ],
      "body": {
        "type": "TextualBody",
        "value": "Saludamos a los heroicos mineros bolivianos que luchan contra el oprobio de siglos. Saludamos al roto chileno que combate a los socios sangrientos de Duarte y los coroneles.",
        "format": "text/plain",
        "purpose": "commenting"
      },
      "target": {
        "source": "https://lgsump.github.io/radio-venceremos-espanol/31-de-diciembre-1981-am/canvas-1/canvas",
        "selector": {
          "type": "RangeSelector",
          "t": "235.0,250.0"
        }
      }
    },
    {
      "@context": "http://www.w3.org/ns/anno.jsonld",
      "id": "31-de-diciembre-1981-am-canvas-1-radio-venceremos-annotation-5.json",
      "type": "Annotation",
      "motivation": [
        "supplementing",
        "commenting"
      ],
      "body": {
        "type": "TextualBody",
        "value": "Saludamos al hombre de la pampa argentina, al obrero pesquero de los mares ajenos en América Latina. Saludamos al indio andino, al indio sin tierra con la esperanza armada en sus manos a un costado del Atitlán guatemalteco. Saludamos al nicaragüense que construye la patria luminosa que le negaron filibusteros y embajadores yanquis. Saludamos al pueblo puertorriqueño que impulsa la lucha anticolonialista.",
        "format": "text/plain",
        "purpose": "commenting"
      },
      "target": {
        "source": "https://lgsump.github.io/radio-venceremos-espanol/31-de-diciembre-1981-am/canvas-1/canvas",
        "selector": {
          "type": "RangeSelector",
          "t": "255.0,289.0"
        }
      }
    },
    {
      "@context": "http://www.w3.org/ns/anno.jsonld",
      "id": "31-de-diciembre-1981-am-canvas-1-radio-venceremos-annotation-6.json",
      "type": "Annotation",
      "motivation": [
        "supplementing",
        "commenting"
      ],
      "body": {
        "type": "TextualBody",
        "value": "Saludamos al pueblo heroico de José Martí, al pueblo de Bolívar, de Sucre. Saludamos a los cristianos comprometidos con los desposeídos del continente. Saludamos a todos los pueblos que hacen de la solidaridad la mano abierta y tendida hacia El Salvador en lucha. Saludamos al heroico pueblo salvadoreño, a la unidad indestructible y necesaria de las fuerzas revolucionarias.",
        "format": "text/plain",
        "purpose": "commenting"
      },
      "target": {
        "source": "https://lgsump.github.io/radio-venceremos-espanol/31-de-diciembre-1981-am/canvas-1/canvas",
        "selector": {
          "type": "RangeSelector",
          "t": "289.0,323.0"
        }
      }
    },
    {
      "@context": "http://www.w3.org/ns/anno.jsonld",
      "id": "31-de-diciembre-1981-am-canvas-1-radio-venceremos-annotation-7.json",
      "type": "Annotation",
      "motivation": [
        "supplementing",
        "commenting"
      ],
      "body": {
        "type": "TextualBody",
        "value": "Saludamos a los hombres y a las mujeres de ese pueblo salvadoreño que avanzó en 1981 hasta las puertas de la victoria y que en 1982, año de otras grandes victorias, ha de vencer la muerte, la violencia, la destrucción de siglos para conquistar la paz en libertad. Saludamos a todos los hombres de la Tierra que como los salvadoreños luchan por el derecho a dejar de ser esclavos de la intervención extranjera, a conquistar el derecho de convertirse en hombres libres sobre una patria soberana.",
        "format": "text/plain",
        "purpose": "commenting"
      },
      "target": {
        "source": "https://lgsump.github.io/radio-venceremos-espanol/31-de-diciembre-1981-am/canvas-1/canvas",
        "selector": {
          "type": "RangeSelector",
          "t": "323.0,368.0"
        }
      }
    },
    {
      "@context": "http://www.w3.org/ns/anno.jsonld",
      "id": "31-de-diciembre-1981-am-canvas-1-radio-venceremos-annotation-8.json",
      "type": "Annotation",
      "motivation": [
        "supplementing",
        "commenting"
      ],
      "body": {
        "type": "TextualBody",
        "value": "Salvadoreños en 1982, organización Venceremos.",
        "format": "text/plain",
        "purpose": "commenting"
      },
      "target": {
        "source": "https://lgsump.github.io/radio-venceremos-espanol/31-de-diciembre-1981-am/canvas-1/canvas",
        "selector": {
          "type": "RangeSelector",
          "t": "371.0,378.0"
        }
      }
    },
    {
      "@context": "http://www.w3.org/ns/anno.jsonld",
      "id": "31-de-diciembre-1981-am-canvas-1-radio-venceremos-annotation-9.json",
      "type": "Annotation",
      "motivation": [
        "supplementing",
        "commenting"
      ],
      "body": {
        "type": "TextualBody",
        "value": "Farabundo Martí, vienes rompiendo caminos libertarios por donde transitarán la paz y la justicia de nuestro pueblo.",
        "format": "text/plain",
        "purpose": "commenting"
      },
      "target": {
        "source": "https://lgsump.github.io/radio-venceremos-espanol/31-de-diciembre-1981-am/canvas-1/canvas",
        "selector": {
          "type": "RangeSelector",
          "t": "419.0,431.0"
        }
      }
    },
    {
      "@context": "http://www.w3.org/ns/anno.jsonld",
      "id": "31-de-diciembre-1981-am-canvas-1-radio-venceremos-annotation-10.json",
      "type": "Annotation",
      "motivation": [
        "supplementing",
        "commenting"
      ],
      "body": {
        "type": "TextualBody",
        "value": "Hermanos unidos para combatir. Avancemos a la revolución. Construyamos un futuro de progreso y dignidad. Revolución o muerte, ¡venceremos!",
        "format": "text/plain",
        "purpose": "commenting"
      },
      "target": {
        "source": "https://lgsump.github.io/radio-venceremos-espanol/31-de-diciembre-1981-am/canvas-1/canvas",
        "selector": {
          "type": "RangeSelector",
          "t": "432.0,454.0"
        }
      }
    },
    {
      "@context": "http://www.w3.org/ns/anno.jsonld",
      "id": "31-de-diciembre-1981-am-canvas-1-radio-venceremos-annotation-11.json",
      "type": "Annotation",
      "motivation": [
        "supplementing",
        "commenting"
      ],
      "body": {
        "type": "TextualBody",
        "value": "¡Venceremos!",
        "format": "text/plain",
        "purpose": "commenting"
      },
      "target": {
        "source": "https://lgsump.github.io/radio-venceremos-espanol/31-de-diciembre-1981-am/canvas-1/canvas",
        "selector": {
          "type": "RangeSelector",
          "t": "454.0,455.0"
        }
      }
    },
    {
      "@context": "http://www.w3.org/ns/anno.jsonld",
      "id": "31-de-diciembre-1981-am-canvas-1-radio-venceremos-annotation-12.json",
      "type": "Annotation",
      "motivation": [
        "supplementing",
        "commenting"
      ],
      "body": {
        "type": "TextualBody",
        "value": "Radio Venceremos presenta un resumen de los principales acontecimientos en 1981, año de avances y victorias para nuestro pueblo.",
        "format": "text/plain",
        "purpose": "commenting"
      },
      "target": {
        "source": "https://lgsump.github.io/radio-venceremos-espanol/31-de-diciembre-1981-am/canvas-1/canvas",
        "selector": {
          "type": "RangeSelector",
          "t": "461.0,472.0"
        }
      }
    },
    {
      "@context": "http://www.w3.org/ns/anno.jsonld",
      "id": "31-de-diciembre-1981-am-canvas-1-radio-venceremos-annotation-13.json",
      "type": "Annotation",
      "motivation": [
        "supplementing",
        "commenting"
      ],
      "body": {
        "type": "TextualBody",
        "value": "Primero de enero, entra en vigor la Ley de Estabilización Económica en un vano intento de solucionar la crisis que vive el país.",
        "format": "text/plain",
        "purpose": "commenting"
      },
      "target": {
        "source": "https://lgsump.github.io/radio-venceremos-espanol/31-de-diciembre-1981-am/canvas-1/canvas",
        "selector": {
          "type": "RangeSelector",
          "t": "475.0,484.0"
        }
      }
    },
    {
      "@context": "http://www.w3.org/ns/anno.jsonld",
      "id": "31-de-diciembre-1981-am-canvas-1-radio-venceremos-annotation-14.json",
      "type": "Annotation",
      "motivation": [
        "supplementing",
        "commenting"
      ],
      "body": {
        "type": "TextualBody",
        "value": "Cuatro de enero. El Frente Democrático Revolucionario nombra a Guillermo Manuel Ungo como presidente y a Eduardo Calles como vicepresidente de esa entidad unitaria.",
        "format": "text/plain",
        "purpose": "commenting"
      },
      "target": {
        "source": "https://lgsump.github.io/radio-venceremos-espanol/31-de-diciembre-1981-am/canvas-1/canvas",
        "selector": {
          "type": "RangeSelector",
          "t": "485.0,498.0"
        }
      }
    },
    {
      "@context": "http://www.w3.org/ns/anno.jsonld",
      "id": "31-de-diciembre-1981-am-canvas-1-radio-venceremos-annotation-15.json",
      "type": "Annotation",
      "motivation": [
        "supplementing",
        "commenting"
      ],
      "body": {
        "type": "TextualBody",
        "value": "Cuatro de enero. Miembros del Escuadrón de la Muerte asesinan a Michael Hammer, asesor del Instituto Norteamericano de Desarrollo y a Mark Pearlinan. En este hecho está involucrado Ricardo Sol.",
        "format": "text/plain",
        "purpose": "commenting"
      },
      "target": {
        "source": "https://lgsump.github.io/radio-venceremos-espanol/31-de-diciembre-1981-am/canvas-1/canvas",
        "selector": {
          "type": "RangeSelector",
          "t": "499.0,514.0"
        }
      }
    },
    {
      "@context": "http://www.w3.org/ns/anno.jsonld",
      "id": "31-de-diciembre-1981-am-canvas-1-radio-venceremos-annotation-16.json",
      "type": "Annotation",
      "motivation": [
        "supplementing",
        "commenting"
      ],
      "body": {
        "type": "TextualBody",
        "value": "Seis de enero. Combatientes del Frente Farabundo Martí para la Liberación Nacional en el cerro de Guazapa derriban avión marca Corsair.",
        "format": "text/plain",
        "purpose": "commenting"
      },
      "target": {
        "source": "https://lgsump.github.io/radio-venceremos-espanol/31-de-diciembre-1981-am/canvas-1/canvas",
        "selector": {
          "type": "RangeSelector",
          "t": "515.0,526.0"
        }
      }
    },
    {
      "@context": "http://www.w3.org/ns/anno.jsonld",
      "id": "31-de-diciembre-1981-am-canvas-1-radio-venceremos-annotation-17.json",
      "type": "Annotation",
      "motivation": [
        "supplementing",
        "commenting"
      ],
      "body": {
        "type": "TextualBody",
        "value": "10 de enero. El Frente Farabundo Martí para la Liberación Nacional hace un llamado a la ofensiva general a través de Radio Venceremos, emisora que en este día sale por primera vez al aire. Nuestras fuerzas activan contra emplazamientos enemigos en diferentes partes del país. Igualmente el 10 de enero se constituye la comisión político-diplomática del Frente Democrático Revolucionario, Frente Farabundo Martí para la Liberación Nacional.",
        "format": "text/plain",
        "purpose": "commenting"
      },
      "target": {
        "source": "https://lgsump.github.io/radio-venceremos-espanol/31-de-diciembre-1981-am/canvas-1/canvas",
        "selector": {
          "type": "RangeSelector",
          "t": "526.0,559.0"
        }
      }
    },
    {
      "@context": "http://www.w3.org/ns/anno.jsonld",
      "id": "31-de-diciembre-1981-am-canvas-1-radio-venceremos-annotation-18.json",
      "type": "Annotation",
      "motivation": [
        "supplementing",
        "commenting"
      ],
      "body": {
        "type": "TextualBody",
        "value": "El mismo 10 de enero la segunda brigada del cuartel de Santana pasa a las filas del Frente Farabundo Martí para la Liberación Nacional después de quemar el cuartel. Los integrantes son dos oficiales, Marcelo Cruz Cruz y Francisco Emilio Mena Sandoval. Junto a ellos se levantan 70 soldados más.",
        "format": "text/plain",
        "purpose": "commenting"
      },
      "target": {
        "source": "https://lgsump.github.io/radio-venceremos-espanol/31-de-diciembre-1981-am/canvas-1/canvas",
        "selector": {
          "type": "RangeSelector",
          "t": "560.0,583.0"
        }
      }
    },
    {
      "@context": "http://www.w3.org/ns/anno.jsonld",
      "id": "31-de-diciembre-1981-am-canvas-1-radio-venceremos-annotation-19.json",
      "type": "Annotation",
      "motivation": [
        "supplementing",
        "commenting"
      ],
      "body": {
        "type": "TextualBody",
        "value": "11 de enero. Es capturada la comandante Lilian Mercedes Letona, en ese momento responsable de las milicias del FMLN en el frente central junto con los compañeros Mario Vigil y Ana Margarita Núñez.",
        "format": "text/plain",
        "purpose": "commenting"
      },
      "target": {
        "source": "https://lgsump.github.io/radio-venceremos-espanol/31-de-diciembre-1981-am/canvas-1/canvas",
        "selector": {
          "type": "RangeSelector",
          "t": "585.0,601.0"
        }
      }
    },
    {
      "@context": "http://www.w3.org/ns/anno.jsonld",
      "id": "31-de-diciembre-1981-am-canvas-1-radio-venceremos-annotation-20.json",
      "type": "Annotation",
      "motivation": [
        "supplementing",
        "commenting"
      ],
      "body": {
        "type": "TextualBody",
        "value": "Este mismo día se toma de la ciudad de Chalatenango y se sitia el cuartel de El Paraíso.",
        "format": "text/plain",
        "purpose": "commenting"
      },
      "target": {
        "source": "https://lgsump.github.io/radio-venceremos-espanol/31-de-diciembre-1981-am/canvas-1/canvas",
        "selector": {
          "type": "RangeSelector",
          "t": "601.0,609.0"
        }
      }
    },
    {
      "@context": "http://www.w3.org/ns/anno.jsonld",
      "id": "31-de-diciembre-1981-am-canvas-1-radio-venceremos-annotation-21.json",
      "type": "Annotation",
      "motivation": [
        "supplementing",
        "commenting"
      ],
      "body": {
        "type": "TextualBody",
        "value": "12 de enero. Fuerzas del Frente Oriental Francisco Sánchez se toman la ciudad de San Francisco Gotera por varias horas.",
        "format": "text/plain",
        "purpose": "commenting"
      },
      "target": {
        "source": "https://lgsump.github.io/radio-venceremos-espanol/31-de-diciembre-1981-am/canvas-1/canvas",
        "selector": {
          "type": "RangeSelector",
          "t": "610.0,619.0"
        }
      }
    },
    {
      "@context": "http://www.w3.org/ns/anno.jsonld",
      "id": "31-de-diciembre-1981-am-canvas-1-radio-venceremos-annotation-22.json",
      "type": "Annotation",
      "motivation": [
        "supplementing",
        "commenting"
      ],
      "body": {
        "type": "TextualBody",
        "value": "Este mismo día fuerzas del Frente Paracentral Anastasio Aquino se toman San Cayetano y Zacatecoluca, San Ildefonso, San Esteban Catarina y San Sebastián simultáneamente.",
        "format": "text/plain",
        "purpose": "commenting"
      },
      "target": {
        "source": "https://lgsump.github.io/radio-venceremos-espanol/31-de-diciembre-1981-am/canvas-1/canvas",
        "selector": {
          "type": "RangeSelector",
          "t": "621.0,636.0"
        }
      }
    },
    {
      "@context": "http://www.w3.org/ns/anno.jsonld",
      "id": "31-de-diciembre-1981-am-canvas-1-radio-venceremos-annotation-23.json",
      "type": "Annotation",
      "motivation": [
        "supplementing",
        "commenting"
      ],
      "body": {
        "type": "TextualBody",
        "value": "15 de enero. Fuerzas combinadas del ejército y cuerpos de seguridad allana el local de la Agencia Independiente de Prensa, AIP, y capturan a la licenciada Vida Cuadra y tres periodistas más.",
        "format": "text/plain",
        "purpose": "commenting"
      },
      "target": {
        "source": "https://lgsump.github.io/radio-venceremos-espanol/31-de-diciembre-1981-am/canvas-1/canvas",
        "selector": {
          "type": "RangeSelector",
          "t": "639.0,654.0"
        }
      }
    },
    {
      "@context": "http://www.w3.org/ns/anno.jsonld",
      "id": "31-de-diciembre-1981-am-canvas-1-radio-venceremos-annotation-24.json",
      "type": "Annotation",
      "motivation": [
        "supplementing",
        "commenting"
      ],
      "body": {
        "type": "TextualBody",
        "value": "17 de enero. Fecha heroica de Cutumay Camones. Mueren en combate 94 combatientes del Frente Farabundo Martí para la Liberación Nacional, entre ellos tres miembros de la dirección de la zona.",
        "format": "text/plain",
        "purpose": "commenting"
      },
      "target": {
        "source": "https://lgsump.github.io/radio-venceremos-espanol/31-de-diciembre-1981-am/canvas-1/canvas",
        "selector": {
          "type": "RangeSelector",
          "t": "655.0,671.0"
        }
      }
    },
    {
      "@context": "http://www.w3.org/ns/anno.jsonld",
      "id": "31-de-diciembre-1981-am-canvas-1-radio-venceremos-annotation-25.json",
      "type": "Annotation",
      "motivation": [
        "supplementing",
        "commenting"
      ],
      "body": {
        "type": "TextualBody",
        "value": "17 de enero. Capturan a nuestro compañero Facundo Guardado en Tegucigalpa, Honduras.",
        "format": "text/plain",
        "purpose": "commenting"
      },
      "target": {
        "source": "https://lgsump.github.io/radio-venceremos-espanol/31-de-diciembre-1981-am/canvas-1/canvas",
        "selector": {
          "type": "RangeSelector",
          "t": "674.0,681.0"
        }
      }
    },
    {
      "@context": "http://www.w3.org/ns/anno.jsonld",
      "id": "31-de-diciembre-1981-am-canvas-1-radio-venceremos-annotation-26.json",
      "type": "Annotation",
      "motivation": [
        "supplementing",
        "commenting"
      ],
      "body": {
        "type": "TextualBody",
        "value": "18 de enero. 700 efectivos de las Fuerzas Armadas allanan el local de la Universidad Centroamericana José Simeón Cañas.",
        "format": "text/plain",
        "purpose": "commenting"
      },
      "target": {
        "source": "https://lgsump.github.io/radio-venceremos-espanol/31-de-diciembre-1981-am/canvas-1/canvas",
        "selector": {
          "type": "RangeSelector",
          "t": "682.0,692.0"
        }
      }
    },
    {
      "@context": "http://www.w3.org/ns/anno.jsonld",
      "id": "31-de-diciembre-1981-am-canvas-1-radio-venceremos-annotation-27.json",
      "type": "Annotation",
      "motivation": [
        "supplementing",
        "commenting"
      ],
      "body": {
        "type": "TextualBody",
        "value": "19 de enero. Fuerzas del FMLN atacan simultáneamente los cuarteles de la Guardia Nacional, Policía Nacional y Marina en Suchitoto, departamento de Cuscatlán.",
        "format": "text/plain",
        "purpose": "commenting"
      },
      "target": {
        "source": "https://lgsump.github.io/radio-venceremos-espanol/31-de-diciembre-1981-am/canvas-1/canvas",
        "selector": {
          "type": "RangeSelector",
          "t": "695.0,708.0"
        }
      }
    },
    {
      "@context": "http://www.w3.org/ns/anno.jsonld",
      "id": "31-de-diciembre-1981-am-canvas-1-radio-venceremos-annotation-28.json",
      "type": "Annotation",
      "motivation": [
        "supplementing",
        "commenting"
      ],
      "body": {
        "type": "TextualBody",
        "value": "25 de enero. Capturan al secretario de la comisión de derechos humanos de El Salvador, Víctor Medrano. Fue liberado posteriormente por la presión popular.",
        "format": "text/plain",
        "purpose": "commenting"
      },
      "target": {
        "source": "https://lgsump.github.io/radio-venceremos-espanol/31-de-diciembre-1981-am/canvas-1/canvas",
        "selector": {
          "type": "RangeSelector",
          "t": "709.0,722.0"
        }
      }
    },
    {
      "@context": "http://www.w3.org/ns/anno.jsonld",
      "id": "31-de-diciembre-1981-am-canvas-1-radio-venceremos-annotation-29.json",
      "type": "Annotation",
      "motivation": [
        "supplementing",
        "commenting"
      ],
      "body": {
        "type": "TextualBody",
        "value": "En los últimos días del mes de enero fue firmado el pacto de convergencia entre la juventud militar y el Frente Farabundo Martí para la Liberación Nacional.",
        "format": "text/plain",
        "purpose": "commenting"
      },
      "target": {
        "source": "https://lgsump.github.io/radio-venceremos-espanol/31-de-diciembre-1981-am/canvas-1/canvas",
        "selector": {
          "type": "RangeSelector",
          "t": "723.0,734.0"
        }
      }
    },
    {
      "@context": "http://www.w3.org/ns/anno.jsonld",
      "id": "31-de-diciembre-1981-am-canvas-1-radio-venceremos-annotation-30.json",
      "type": "Annotation",
      "motivation": [
        "supplementing",
        "commenting"
      ],
      "body": {
        "type": "TextualBody",
        "value": "20 de febrero. Capturan al coronel Adolfo Majano en la ciudad de Guatemala. Es extraditado a El Salvador. Duarte asegura, \"Se hará juicio militar\".",
        "format": "text/plain",
        "purpose": "commenting"
      },
      "target": {
        "source": "https://lgsump.github.io/radio-venceremos-espanol/31-de-diciembre-1981-am/canvas-1/canvas",
        "selector": {
          "type": "RangeSelector",
          "t": "740.0,753.0"
        }
      }
    },
    {
      "@context": "http://www.w3.org/ns/anno.jsonld",
      "id": "31-de-diciembre-1981-am-canvas-1-radio-venceremos-annotation-31.json",
      "type": "Annotation",
      "motivation": [
        "supplementing",
        "commenting"
      ],
      "body": {
        "type": "TextualBody",
        "value": "23 de febrero. El Departamento de Estado de los Estados Unidos hizo público el libro blanco en un intento de justificar la intervención de los Estados Unidos en El Salvador.",
        "format": "text/plain",
        "purpose": "commenting"
      },
      "target": {
        "source": "https://lgsump.github.io/radio-venceremos-espanol/31-de-diciembre-1981-am/canvas-1/canvas",
        "selector": {
          "type": "RangeSelector",
          "t": "754.0,767.0"
        }
      }
    },
    {
      "@context": "http://www.w3.org/ns/anno.jsonld",
      "id": "31-de-diciembre-1981-am-canvas-1-radio-venceremos-annotation-32.json",
      "type": "Annotation",
      "motivation": [
        "supplementing",
        "commenting"
      ],
      "body": {
        "type": "TextualBody",
        "value": "24 de febrero. Voladura del polvorín de la Tercera Brigada de Infantería en San Miguel.",
        "format": "text/plain",
        "purpose": "commenting"
      },
      "target": {
        "source": "https://lgsump.github.io/radio-venceremos-espanol/31-de-diciembre-1981-am/canvas-1/canvas",
        "selector": {
          "type": "RangeSelector",
          "t": "768.0,775.0"
        }
      }
    },
    {
      "@context": "http://www.w3.org/ns/anno.jsonld",
      "id": "31-de-diciembre-1981-am-canvas-1-radio-venceremos-annotation-33.json",
      "type": "Annotation",
      "motivation": [
        "supplementing",
        "commenting"
      ],
      "body": {
        "type": "TextualBody",
        "value": "Día 27. El FMLV presenta al prisionero de guerra Santos Enrique Díaz Alvarenga de 22 años de edad, destacado en la Tercera Brigada de Infantería en San Miguel.",
        "format": "text/plain",
        "purpose": "commenting"
      },
      "target": {
        "source": "https://lgsump.github.io/radio-venceremos-espanol/31-de-diciembre-1981-am/canvas-1/canvas",
        "selector": {
          "type": "RangeSelector",
          "t": "776.0,788.0"
        }
      }
    },
    {
      "@context": "http://www.w3.org/ns/anno.jsonld",
      "id": "31-de-diciembre-1981-am-canvas-1-radio-venceremos-annotation-34.json",
      "type": "Annotation",
      "motivation": [
        "supplementing",
        "commenting"
      ],
      "body": {
        "type": "TextualBody",
        "value": "Primero de marzo. Los comandantes Fermán Cienfuegos y Joaquín Villalobos del Frente Farabundo Martí para la Liberación Nacional se reúnen con el señor Carlson, secretario general de la Internacional Socialista para presentarle un análisis de la situación salvadoreña. La reunión se efectuó en Panamá.",
        "format": "text/plain",
        "purpose": "commenting"
      },
      "target": {
        "source": "https://lgsump.github.io/radio-venceremos-espanol/31-de-diciembre-1981-am/canvas-1/canvas",
        "selector": {
          "type": "RangeSelector",
          "t": "789.0,812.0"
        }
      }
    },
    {
      "@context": "http://www.w3.org/ns/anno.jsonld",
      "id": "31-de-diciembre-1981-am-canvas-1-radio-venceremos-annotation-35.json",
      "type": "Annotation",
      "motivation": [
        "supplementing",
        "commenting"
      ],
      "body": {
        "type": "TextualBody",
        "value": "El seis se cierra oficialmente en Costa Rica a Radio Noticias del Continente.",
        "format": "text/plain",
        "purpose": "commenting"
      },
      "target": {
        "source": "https://lgsump.github.io/radio-venceremos-espanol/31-de-diciembre-1981-am/canvas-1/canvas",
        "selector": {
          "type": "RangeSelector",
          "t": "813.0,819.0"
        }
      }
    },
    {
      "@context": "http://www.w3.org/ns/anno.jsonld",
      "id": "31-de-diciembre-1981-am-canvas-1-radio-venceremos-annotation-36.json",
      "type": "Annotation",
      "motivation": [
        "supplementing",
        "commenting"
      ],
      "body": {
        "type": "TextualBody",
        "value": "Nueve de marzo. Fuerzas del ejército de la junta militar democristiana inicia ofensiva en el departamento de Morazán.",
        "format": "text/plain",
        "purpose": "commenting"
      },
      "target": {
        "source": "https://lgsump.github.io/radio-venceremos-espanol/31-de-diciembre-1981-am/canvas-1/canvas",
        "selector": {
          "type": "RangeSelector",
          "t": "820.0,829.0"
        }
      }
    },
    {
      "@context": "http://www.w3.org/ns/anno.jsonld",
      "id": "31-de-diciembre-1981-am-canvas-1-radio-venceremos-annotation-37.json",
      "type": "Annotation",
      "motivation": [
        "supplementing",
        "commenting"
      ],
      "body": {
        "type": "TextualBody",
        "value": "24 de marzo. En el primer aniversario de la muerte de monseñor Óscar Arnulfo Romero la comandancia general del Frente Farabundo Martí para la Liberación Nacional ordena un cese al fuego en honor al obispo mártir.",
        "format": "text/plain",
        "purpose": "commenting"
      },
      "target": {
        "source": "https://lgsump.github.io/radio-venceremos-espanol/31-de-diciembre-1981-am/canvas-1/canvas",
        "selector": {
          "type": "RangeSelector",
          "t": "831.0,848.0"
        }
      }
    },
    {
      "@context": "http://www.w3.org/ns/anno.jsonld",
      "id": "31-de-diciembre-1981-am-canvas-1-radio-venceremos-annotation-38.json",
      "type": "Annotation",
      "motivation": [
        "supplementing",
        "commenting"
      ],
      "body": {
        "type": "TextualBody",
        "value": "25 de marzo. Masacre en la cueva de la pintada a inmediaciones de Chalatenango, sector fronterizo con Honduras.",
        "format": "text/plain",
        "purpose": "commenting"
      },
      "target": {
        "source": "https://lgsump.github.io/radio-venceremos-espanol/31-de-diciembre-1981-am/canvas-1/canvas",
        "selector": {
          "type": "RangeSelector",
          "t": "849.0,858.0"
        }
      }
    },
    {
      "@context": "http://www.w3.org/ns/anno.jsonld",
      "id": "31-de-diciembre-1981-am-canvas-1-radio-venceremos-annotation-39.json",
      "type": "Annotation",
      "motivation": [
        "supplementing",
        "commenting"
      ],
      "body": {
        "type": "TextualBody",
        "value": "El 31 de marzo fuerzas del Frente Oriental Francisco Sánchez rompen el cerco militar de la dictadura y vencen un gigantesco operativo contra el departamento de Morazán.",
        "format": "text/plain",
        "purpose": "commenting"
      },
      "target": {
        "source": "https://lgsump.github.io/radio-venceremos-espanol/31-de-diciembre-1981-am/canvas-1/canvas",
        "selector": {
          "type": "RangeSelector",
          "t": "859.0,870.0"
        }
      }
    },
    {
      "@context": "http://www.w3.org/ns/anno.jsonld",
      "id": "31-de-diciembre-1981-am-canvas-1-radio-venceremos-annotation-40.json",
      "type": "Annotation",
      "motivation": [
        "supplementing",
        "commenting"
      ],
      "body": {
        "type": "TextualBody",
        "value": "Atención, Radio Venceremos en esta transmisión dará a conocer el comunicado de la comandancia general del Frente Farabundo Martí para la Liberación Nacional con motivo del fin de año.",
        "format": "text/plain",
        "purpose": "commenting"
      },
      "target": {
        "source": "https://lgsump.github.io/radio-venceremos-espanol/31-de-diciembre-1981-am/canvas-1/canvas",
        "selector": {
          "type": "RangeSelector",
          "t": "880.0,895.0"
        }
      }
    },
    {
      "@context": "http://www.w3.org/ns/anno.jsonld",
      "id": "31-de-diciembre-1981-am-canvas-1-radio-venceremos-annotation-41.json",
      "type": "Annotation",
      "motivation": [
        "supplementing",
        "commenting"
      ],
      "body": {
        "type": "TextualBody",
        "value": "Escuchamos al compañero sacerdote Rogelio Ponseele en un mensaje a nuestro pueblo cristiano.",
        "format": "text/plain",
        "purpose": "commenting"
      },
      "target": {
        "source": "https://lgsump.github.io/radio-venceremos-espanol/31-de-diciembre-1981-am/canvas-1/canvas",
        "selector": {
          "type": "RangeSelector",
          "t": "1380.0,1388.0"
        }
      }
    },
    {
      "@context": "http://www.w3.org/ns/anno.jsonld",
      "id": "31-de-diciembre-1981-am-canvas-1-radio-venceremos-annotation-42.json",
      "type": "Annotation",
      "motivation": [
        "supplementing",
        "commenting"
      ],
      "body": {
        "type": "TextualBody",
        "value": "Ahora hacemos contacto con una de nuestras unidades móviles, la cual desde la población de El Mozote trae nuevos testimonios sobre la masacre efectuada por la dictadura en el departamento de Morazán donde asesinó a sangre fría a alrededor de 1.000 campesinos salvadoreños. Adelante, compañeros.",
        "format": "text/plain",
        "purpose": "commenting"
      },
      "target": {
        "source": "https://lgsump.github.io/radio-venceremos-espanol/31-de-diciembre-1981-am/canvas-1/canvas",
        "selector": {
          "type": "RangeSelector",
          "t": "1425.0,1448.0"
        }
      }
    },
    {
      "@context": "http://www.w3.org/ns/anno.jsonld",
      "id": "31-de-diciembre-1981-am-canvas-1-radio-venceremos-annotation-43.json",
      "type": "Annotation",
      "motivation": [
        "supplementing",
        "commenting"
      ],
      "body": {
        "type": "TextualBody",
        "value": "Emplazamos de nuevo al presidente de la Junta Militar Democratacristiana, ingeniero José Napoleón Duarte a que desmienta Radio Venceremos de que toda la población de El Mozote, mujeres, hombres, ancianos y niños fueron masacrados fríamente por las tropas al mando del mayor Cáceres.",
        "format": "text/plain",
        "purpose": "commenting"
      },
      "target": {
        "source": "https://lgsump.github.io/radio-venceremos-espanol/31-de-diciembre-1981-am/canvas-1/canvas",
        "selector": {
          "type": "RangeSelector",
          "t": "1982.0,2006.0"
        }
      }
    },
    {
      "@context": "http://www.w3.org/ns/anno.jsonld",
      "id": "31-de-diciembre-1981-am-canvas-1-radio-venceremos-annotation-44.json",
      "type": "Annotation",
      "motivation": [
        "supplementing",
        "commenting"
      ],
      "body": {
        "type": "TextualBody",
        "value": "El pueblo salvadoreño ha dado muestras de una gran heroicidad y de una elevada capacidad combativa. A pesar de las decenas de miles de salvadoreños muertos, continúa y fortalece su lucha libertaria. Hemos vivido muchos ejemplos de coraje y valentía.",
        "format": "text/plain",
        "purpose": "commenting"
      },
      "target": {
        "source": "https://lgsump.github.io/radio-venceremos-espanol/31-de-diciembre-1981-am/canvas-1/canvas",
        "selector": {
          "type": "RangeSelector",
          "t": "2017.0,2040.0"
        }
      }
    },
    {
      "@context": "http://www.w3.org/ns/anno.jsonld",
      "id": "31-de-diciembre-1981-am-canvas-1-radio-venceremos-annotation-45.json",
      "type": "Annotation",
      "motivation": [
        "supplementing",
        "commenting"
      ],
      "body": {
        "type": "TextualBody",
        "value": "El recién pasado 29 de diciembre, fecha en que los compañeros Elmer, Serapio y Edwin cayeron en los victoriosos combates de la Guacamaya en el departamento de Morazán dando así muestras claras de su agresividad revolucionaria, afianzadas en una indoblegable decisión de vencer y una profunda confianza en la victoria. Ellos nos han legado el ejemplo de revolucionarios, que a pesar de su alta capacidad combativa, nunca perdieron su sencillez y modestia. Son cualidades fundamentales de luchadores proletarios.",
        "format": "text/plain",
        "purpose": "commenting"
      },
      "target": {
        "source": "https://lgsump.github.io/radio-venceremos-espanol/31-de-diciembre-1981-am/canvas-1/canvas",
        "selector": {
          "type": "RangeSelector",
          "t": "2041.0,2083.0"
        }
      }
    },
    {
      "@context": "http://www.w3.org/ns/anno.jsonld",
      "id": "31-de-diciembre-1981-am-canvas-1-radio-venceremos-annotation-46.json",
      "type": "Annotation",
      "motivation": [
        "supplementing",
        "commenting"
      ],
      "body": {
        "type": "TextualBody",
        "value": "Su consecuencia los llevó a cumplir con su compromiso con el pueblo salvadoreño llegando al máximo compromiso de legar hasta su propia vida. El Frente Oriental Francisco Sánchez ha perdido a tres de sus mejores combatientes, pero estamos seguros que otros ya llenarán el espacio vacío dejado por los compañeros y muchos más seguirán el ejemplo de su decisión de vencer o morir. Unidos para combatir, hasta la victoria final. Revolución o muerte, venceremos. Frente Oriental Francisco Sánchez, zona sur.",
        "format": "text/plain",
        "purpose": "commenting"
      },
      "target": {
        "source": "https://lgsump.github.io/radio-venceremos-espanol/31-de-diciembre-1981-am/canvas-1/canvas",
        "selector": {
          "type": "RangeSelector",
          "t": "2084.0,2126.0"
        }
      }
    },
    {
      "@context": "http://www.w3.org/ns/anno.jsonld",
      "id": "31-de-diciembre-1981-am-canvas-1-radio-venceremos-annotation-47.json",
      "type": "Annotation",
      "motivation": [
        "supplementing",
        "commenting"
      ],
      "body": {
        "type": "TextualBody",
        "value": "A continuación, Radio Venceremos, premio 1981 de la Organización Internacional de Periodistas presenta Plomo Informativo.",
        "format": "text/plain",
        "purpose": "commenting"
      },
      "target": {
        "source": "https://lgsump.github.io/radio-venceremos-espanol/31-de-diciembre-1981-am/canvas-1/canvas",
        "selector": {
          "type": "RangeSelector",
          "t": "2135.0,2147.0"
        }
      }
    }
  ]
}